funniest/__init__.py
liangzhi/__init__.py
liangzhi-0.1.dist-info/METADATA
liangzhi-0.1.dist-info/WHEEL
liangzhi-0.1.dist-info/top_level.txt
liangzhi-0.1.dist-info/RECORD
