Metadata-Version: 2.1
Name: liangzhi
Version: 0.1
Summary: The funniest joke in the world
Home-page: http://github.com/username/repo
Author: Your Name
Author-email: yourname@quant-chi.com
License: MIT
Platform: UNKNOWN
